blueonion/VERSION.txt
blueonion/__init__.py
blueonion/dataapi/__init__.py
blueonion/dataapi/client.py
blueonion/dataapi/data_pro.py
blueonion-1.0.2.dist-info/METADATA
blueonion-1.0.2.dist-info/WHEEL
blueonion-1.0.2.dist-info/top_level.txt
blueonion-1.0.2.dist-info/RECORD
