Metadata-Version: 2.1
Name: blueonion
Version: 1.0.2
Summary: A utility for crawling historical and Real-time Quotes data of China stocks
Home-page: http://54.169.163.141:8099/
Author: gmcheng
Author-email: chenggm2002@163.com
License: BSD
Keywords: Global Financial Data
Platform: UNKNOWN
Classifier: Development Status :: 4 - Beta
Classifier: Programming Language :: Python :: 2.6
Classifier: Programming Language :: Python :: 2.7
Classifier: Programming Language :: Python :: 3.2
Classifier: Programming Language :: Python :: 3.3
Classifier: Programming Language :: Python :: 3.4
Classifier: Programming Language :: Python :: 3.5
Classifier: License :: OSI Approved :: BSD License
Requires-Dist: requests (>=2.0.0)
Requires-Dist: simplejson (>=3.16.0)
